<?xml version="1.0"?>
<game file="/Users/richsanda/life/python/crawlers/espn/games/2005.11.1.xml"><team><header>Jeff Knight All-Stars Box Score</header><players><player id="plyr60029"><player-name>Panthers D/ST, Car&#xA0;D/ST</player-name><link>&lt;a href content="ajax#/ffl/format/pvopop/summary?leagueId=35734&amp;positionId=16&amp;playerId=71603&amp;seasonId=2005" class="flexpop" instance="_ppc"&gt;@Chi&lt;/a&gt;</link><opponent>@Chi</opponent><game-status>L 3-13</game-status><points>6</points></player><player id="plyr5362"><player-name>Antonio Gates, SD&#xA0;TE</player-name><link>&lt;a href content="ajax#/ffl/format/pvopop/summary?leagueId=35734&amp;positionId=4&amp;playerId=70402&amp;seasonId=2005" class="flexpop" instance="_ppc"&gt;Buf&lt;/a&gt;</link><opponent>Buf</opponent><game-status>W 48-10</game-status><points>13</points></player><player id="plyr112"><player-name>Brett Favre, GB&#xA0;QB</player-name><link>&lt;a href content="ajax#/ffl/format/pvopop/summary?leagueId=35734&amp;positionId=1&amp;playerId=70116&amp;seasonId=2005" class="flexpop" instance="_ppc"&gt;Min&lt;/a&gt;</link><opponent>Min</opponent><game-status>L 17-20</game-status><points>15</points></player><player id="plyr5528"><player-name>Larry Fitzgerald, Ari&#xA0;WR</player-name><link>&lt;a href content="ajax#/ffl/format/pvopop/summary?leagueId=35734&amp;positionId=3&amp;playerId=70314&amp;seasonId=2005" class="flexpop" instance="_ppc"&gt;@StL&lt;/a&gt;</link><opponent>@StL</opponent><game-status>W 38-28</game-status><points>18</points></player><player id="plyr2584"><player-name>Chad Johnson, Cin&#xA0;WR</player-name><link>&lt;a href content="ajax#/ffl/format/pvopop/summary?leagueId=35734&amp;positionId=3&amp;playerId=70311&amp;seasonId=2005" class="flexpop" instance="_ppc"&gt;Ind&lt;/a&gt;</link><opponent>Ind</opponent><game-status>L 37-45</game-status><points>28</points></player><player id="plyr726"><player-name>Jeff Wilkins, StL&#xA0;K</player-name><link>&lt;a href content="ajax#/ffl/format/pvopop/summary?leagueId=35734&amp;positionId=5&amp;playerId=70522&amp;seasonId=2005" class="flexpop" instance="_ppc"&gt;Ari&lt;/a&gt;</link><opponent>Ari</opponent><game-status>L 28-38</game-status><points>9</points></player><player id="plyr4485"><player-name>Larry Johnson, KC&#xA0;RB</player-name><link>&lt;a href content="ajax#/ffl/format/pvopop/summary?leagueId=35734&amp;positionId=2&amp;playerId=70234&amp;seasonId=2005" class="flexpop" instance="_ppc"&gt;@Hou&lt;/a&gt;</link><opponent>@Hou</opponent><game-status>W 45-17</game-status><points>37</points></player><player id="plyr3579"><player-name>Clinton Portis, Was&#xA0;RB</player-name><link>&lt;a href content="ajax#/ffl/format/pvopop/summary?leagueId=35734&amp;positionId=2&amp;playerId=70213&amp;seasonId=2005" class="flexpop" instance="_ppc"&gt;Oak&lt;/a&gt;</link><opponent>Oak</opponent><game-status>L 13-16</game-status><points>5</points></player></players></team><team><header>Bridgewater Raritan Box Score</header><players><player id="plyr5590"><player-name>Nate Kaeding, SD&#xA0;K</player-name><link>&lt;a href content="ajax#/ffl/format/pvopop/summary?leagueId=35734&amp;positionId=5&amp;playerId=70502&amp;seasonId=2005" class="flexpop" instance="_ppc"&gt;Buf&lt;/a&gt;</link><opponent>Buf</opponent><game-status>W 48-10</game-status><points>12</points></player><player id="plyr2580"><player-name>Drew Brees, SD&#xA0;QB</player-name><link>&lt;a href content="ajax#/ffl/format/pvopop/summary?leagueId=35734&amp;positionId=1&amp;playerId=70102&amp;seasonId=2005" class="flexpop" instance="_ppc"&gt;Buf&lt;/a&gt;</link><opponent>Buf</opponent><game-status>W 48-10</game-status><points>31</points></player><player id="plyr5555"><player-name>Kevin Jones, Det&#xA0;RB</player-name><link>&lt;a href content="ajax#/ffl/format/pvopop/summary?leagueId=35734&amp;positionId=2&amp;playerId=70206&amp;seasonId=2005" class="flexpop" instance="_ppc"&gt;@Dal&lt;/a&gt;</link><opponent>@Dal</opponent><game-status>L 7-20</game-status><points>11</points></player><player id="plyr939"><player-name>Marvin Harrison, Ind&#xA0;WR</player-name><link>&lt;a href content="ajax#/ffl/format/pvopop/summary?leagueId=35734&amp;positionId=3&amp;playerId=70304&amp;seasonId=2005" class="flexpop" instance="_ppc"&gt;@Cin&lt;/a&gt;</link><opponent>@Cin</opponent><game-status>W 45-37</game-status><points>4</points></player><player id="plyr60026"><player-name>Seahawks D/ST, Sea&#xA0;D/ST</player-name><link>&lt;a href content="ajax#/ffl/format/pvopop/summary?leagueId=35734&amp;positionId=16&amp;playerId=71625&amp;seasonId=2005" class="flexpop" instance="_ppc"&gt;@SF&lt;/a&gt;</link><opponent>@SF</opponent><game-status>W 27-25</game-status><points>5</points></player><player id="plyr8436"><player-name>Matt Jones, Jac&#xA0;WR</player-name><link>&lt;a href content="ajax#/ffl/format/pvopop/summary?leagueId=35734&amp;positionId=3&amp;playerId=70310&amp;seasonId=2005" class="flexpop" instance="_ppc"&gt;@Ten&lt;/a&gt;</link><opponent>@Ten</opponent><game-status>W 31-28</game-status><points>10</points></player><player id="plyr1231"><player-name>Tony Gonzalez, KC&#xA0;TE</player-name><link>&lt;a href content="ajax#/ffl/format/pvopop/summary?leagueId=35734&amp;positionId=4&amp;playerId=70434&amp;seasonId=2005" class="flexpop" instance="_ppc"&gt;@Hou&lt;/a&gt;</link><opponent>@Hou</opponent><game-status>W 45-17</game-status><points>9</points></player><player id="plyr2212"><player-name>Reuben Droughns, Cle&#xA0;RB</player-name><link>&lt;a href content="ajax#/ffl/format/pvopop/summary?leagueId=35734&amp;positionId=2&amp;playerId=70215&amp;seasonId=2005" class="flexpop" instance="_ppc"&gt;Mia&lt;/a&gt;</link><opponent>Mia</opponent><game-status>W 22-0</game-status><points>26</points></player></players></team></game>
