<?xml version="1.0"?>
<game file="/Users/richsanda/life/python/crawlers/espn/games/2006.10.7.xml"><team><header>Apponequet Justins Box Score</header><players><player id="plyr1097"><player-name>Adam Vinatieri, Ind&#xA0;K</player-name><link>&lt;a href content="ajax#/ffl/format/pvopop/summary?leagueId=35734&amp;positionId=5&amp;playerId=70502&amp;seasonId=2006" class="flexpop" instance="_ppc"&gt;Buf&lt;/a&gt;</link><opponent>Buf</opponent><game-status>W 17-16</game-status><points>5</points></player><player id="plyr5362"><player-name>Antonio Gates, SD&#xA0;TE</player-name><link>&lt;a href content="ajax#/ffl/format/pvopop/summary?leagueId=35734&amp;positionId=4&amp;playerId=70404&amp;seasonId=2006" class="flexpop" instance="_ppc"&gt;@Cin&lt;/a&gt;</link><opponent>@Cin</opponent><game-status>W 49-41</game-status><points>6</points></player><player id="plyr2553"><player-name>LaDainian Tomlinson, SD&#xA0;RB</player-name><link>&lt;a href content="ajax#/ffl/format/pvopop/summary?leagueId=35734&amp;positionId=2&amp;playerId=70204&amp;seasonId=2006" class="flexpop" instance="_ppc"&gt;@Cin&lt;/a&gt;</link><opponent>@Cin</opponent><game-status>W 49-41</game-status><points>41</points></player><player id="plyr60011"><player-name>Colts D/ST, Ind&#xA0;D/ST</player-name><link>&lt;a href content="ajax#/ffl/format/pvopop/summary?leagueId=35734&amp;positionId=16&amp;playerId=71602&amp;seasonId=2006" class="flexpop" instance="_ppc"&gt;Buf&lt;/a&gt;</link><opponent>Buf</opponent><game-status>W 17-16</game-status><points>5</points></player><player id="plyr5529"><player-name>Philip Rivers, SD&#xA0;QB</player-name><link>&lt;a href content="ajax#/ffl/format/pvopop/summary?leagueId=35734&amp;positionId=1&amp;playerId=70104&amp;seasonId=2006" class="flexpop" instance="_ppc"&gt;@Cin&lt;/a&gt;</link><opponent>@Cin</opponent><game-status>W 49-41</game-status><points>29</points></player><player id="plyr1432"><player-name>Ahman Green, GB&#xA0;RB</player-name><link>&lt;a href content="ajax#/ffl/format/pvopop/summary?leagueId=35734&amp;positionId=2&amp;playerId=70216&amp;seasonId=2006" class="flexpop" instance="_ppc"&gt;@Min&lt;/a&gt;</link><opponent>@Min</opponent><game-status>W 23-17</game-status><points>5</points></player><player id="plyr1966"><player-name>Donald Driver, GB&#xA0;WR</player-name><link>&lt;a href content="ajax#/ffl/format/pvopop/summary?leagueId=35734&amp;positionId=3&amp;playerId=70316&amp;seasonId=2006" class="flexpop" instance="_ppc"&gt;@Min&lt;/a&gt;</link><opponent>@Min</opponent><game-status>W 23-17</game-status><points>29</points></player><player id="plyr2584"><player-name>Chad Johnson, Cin&#xA0;WR</player-name><link>&lt;a href content="ajax#/ffl/format/pvopop/summary?leagueId=35734&amp;positionId=3&amp;playerId=70324&amp;seasonId=2006" class="flexpop" instance="_ppc"&gt;SD&lt;/a&gt;</link><opponent>SD</opponent><game-status>L 41-49</game-status><points>46</points></player></players></team><team><header>Windy City Heat Box Score</header><players><player id="plyr60029"><player-name>Panthers D/ST, Car&#xA0;D/ST</player-name><link>&lt;a href content="ajax#/ffl/format/pvopop/summary?leagueId=35734&amp;positionId=16&amp;playerId=71627&amp;seasonId=2006" class="flexpop" instance="_ppc"&gt;TB&lt;/a&gt;</link><opponent>TB</opponent><game-status>W 24-10</game-status><points>15</points></player><player id="plyr8616"><player-name>Dave Rayner, GB&#xA0;K</player-name><link>&lt;a href content="ajax#/ffl/format/pvopop/summary?leagueId=35734&amp;positionId=5&amp;playerId=70516&amp;seasonId=2006" class="flexpop" instance="_ppc"&gt;@Min&lt;/a&gt;</link><opponent>@Min</opponent><game-status>W 23-17</game-status><points>11</points></player><player id="plyr1430"><player-name>Fred Taylor, Jac&#xA0;RB</player-name><link>&lt;a href content="ajax#/ffl/format/pvopop/summary?leagueId=35734&amp;positionId=2&amp;playerId=70234&amp;seasonId=2006" class="flexpop" instance="_ppc"&gt;Hou&lt;/a&gt;</link><opponent>Hou</opponent><game-status>L 10-13</game-status><points>13</points></player><player id="plyr5209"><player-name>Tony Romo, Dal&#xA0;QB</player-name><link>&lt;a href content="ajax#/ffl/format/pvopop/summary?leagueId=35734&amp;positionId=1&amp;playerId=70122&amp;seasonId=2006" class="flexpop" instance="_ppc"&gt;@Ari&lt;/a&gt;</link><opponent>@Ari</opponent><game-status>W 27-10</game-status><points>24</points></player><player id="plyr3593"><player-name>Deion Branch, Sea&#xA0;WR</player-name><link>&lt;a href content="ajax#/ffl/format/pvopop/summary?leagueId=35734&amp;positionId=3&amp;playerId=70314&amp;seasonId=2006" class="flexpop" instance="_ppc"&gt;StL&lt;/a&gt;</link><opponent>StL</opponent><game-status>W 24-22</game-status><points>2</points></player><player id="plyr2579"><player-name>Todd Heap, Bal&#xA0;TE</player-name><link>&lt;a href content="ajax#/ffl/format/pvopop/summary?leagueId=35734&amp;positionId=4&amp;playerId=70410&amp;seasonId=2006" class="flexpop" instance="_ppc"&gt;@Ten&lt;/a&gt;</link><opponent>@Ten</opponent><game-status>W 27-26</game-status><points>4</points></player><player id="plyr3591"><player-name>Antonio Bryant, SF&#xA0;WR</player-name><link>&lt;a href content="ajax#/ffl/format/pvopop/summary?leagueId=35734&amp;positionId=3&amp;playerId=70308&amp;seasonId=2006" class="flexpop" instance="_ppc"&gt;@Det&lt;/a&gt;</link><opponent>@Det</opponent><game-status>W 19-13</game-status><points>4</points></player><player id="plyr2136"><player-name>Jamal Lewis, Bal&#xA0;RB</player-name><link>&lt;a href content="ajax#/ffl/format/pvopop/summary?leagueId=35734&amp;positionId=2&amp;playerId=70210&amp;seasonId=2006" class="flexpop" instance="_ppc"&gt;@Ten&lt;/a&gt;</link><opponent>@Ten</opponent><game-status>W 27-26</game-status><points>4</points></player></players></team></game>
