<?xml version="1.0"?>
<game file="/Users/richsanda/life/python/crawlers/espn/games/2008.14.4.xml"><team><header>Magoun Square Ruffians Box Score</header><players><player id="plyr5679"><player-name>Michael Turner, Atl&#xA0;RB</player-name><link>&lt;a href content="ajax#/ffl/format/pvopop/summary?leagueId=35734&amp;positionId=2&amp;playerId=70218&amp;seasonId=2008" class="flexpop" instance="_ppc"&gt;@NO&lt;/a&gt;</link><opponent>@NO</opponent><game-status>L 25-29</game-status><points>12</points></player><player id="plyr60033"><player-name>Ravens D/ST, Bal&#xA0;D/ST</player-name><link>&lt;a href content="ajax#/ffl/format/pvopop/summary?leagueId=35734&amp;positionId=16&amp;playerId=71628&amp;seasonId=2008" class="flexpop" instance="_ppc"&gt;Was&lt;/a&gt;</link><opponent>Was</opponent><game-status>W 24-10</game-status><points>18</points></player><player id="plyr4333"><player-name>Matt Bryant, TB&#xA0;K</player-name><link>&lt;a href content="ajax#/ffl/format/pvopop/summary?leagueId=35734&amp;positionId=5&amp;playerId=70529&amp;seasonId=2008" class="flexpop" instance="_ppc"&gt;@Car&lt;/a&gt;</link><opponent>@Car</opponent><game-status>L 23-38</game-status><points>2</points></player><player id="plyr1682"><player-name>Kurt Warner, Ari&#xA0;QB</player-name><link>&lt;a href content="ajax#/ffl/format/pvopop/summary?leagueId=35734&amp;positionId=1&amp;playerId=70114&amp;seasonId=2008" class="flexpop" instance="_ppc"&gt;StL&lt;/a&gt;</link><opponent>StL</opponent><game-status>W 34-10</game-status><points>13</points></player><player id="plyr11383"><player-name>Tim Hightower, Ari&#xA0;RB</player-name><link>&lt;a href content="ajax#/ffl/format/pvopop/summary?leagueId=35734&amp;positionId=2&amp;playerId=70214&amp;seasonId=2008" class="flexpop" instance="_ppc"&gt;StL&lt;/a&gt;</link><opponent>StL</opponent><game-status>W 34-10</game-status><points>9</points></player><player id="plyr1056"><player-name>Terrell Owens, Dal&#xA0;WR</player-name><link>&lt;a href content="ajax#/ffl/format/pvopop/summary?leagueId=35734&amp;positionId=3&amp;playerId=70323&amp;seasonId=2008" class="flexpop" instance="_ppc"&gt;@Pit&lt;/a&gt;</link><opponent>@Pit</opponent><game-status>L 13-20</game-status><points>9</points></player><player id="plyr1231"><player-name>Tony Gonzalez, KC&#xA0;TE</player-name><link>&lt;a href content="ajax#/ffl/format/pvopop/summary?leagueId=35734&amp;positionId=4&amp;playerId=70407&amp;seasonId=2008" class="flexpop" instance="_ppc"&gt;@Den&lt;/a&gt;</link><opponent>@Den</opponent><game-status>L 17-24</game-status><points>13</points></player><player id="plyr9705"><player-name>Brandon Marshall, Den&#xA0;WR</player-name><link>&lt;a href content="ajax#/ffl/format/pvopop/summary?leagueId=35734&amp;positionId=3&amp;playerId=70312&amp;seasonId=2008" class="flexpop" instance="_ppc"&gt;KC&lt;/a&gt;</link><opponent>KC</opponent><game-status>W 24-17</game-status><points>21</points></player></players></team><team><header>Jeff Knight All-Stars Box Score</header><players><player id="plyr11258"><player-name>Chris Johnson, Ten&#xA0;RB</player-name><link>&lt;a href content="ajax#/ffl/format/pvopop/summary?leagueId=35734&amp;positionId=2&amp;playerId=70205&amp;seasonId=2008" class="flexpop" instance="_ppc"&gt;Cle&lt;/a&gt;</link><opponent>Cle</opponent><game-status>W 28-9</game-status><points>24</points></player><player id="plyr60015"><player-name>Dolphins D/ST, Mia&#xA0;D/ST</player-name><link>&lt;a href content="ajax#/ffl/format/pvopop/summary?leagueId=35734&amp;positionId=16&amp;playerId=71602&amp;seasonId=2008" class="flexpop" instance="_ppc"&gt;@Buf&lt;/a&gt;</link><opponent>@Buf</opponent><game-status>W 16-3</game-status><points>15</points></player><player id="plyr5209"><player-name>Tony Romo, Dal&#xA0;QB</player-name><link>&lt;a href content="ajax#/ffl/format/pvopop/summary?leagueId=35734&amp;positionId=1&amp;playerId=70123&amp;seasonId=2008" class="flexpop" instance="_ppc"&gt;@Pit&lt;/a&gt;</link><opponent>@Pit</opponent><game-status>L 13-20</game-status><points>4</points></player><player id="plyr4461"><player-name>Andre Johnson, Hou&#xA0;WR</player-name><link>&lt;a href content="ajax#/ffl/format/pvopop/summary?leagueId=35734&amp;positionId=3&amp;playerId=70309&amp;seasonId=2008" class="flexpop" instance="_ppc"&gt;@GB&lt;/a&gt;</link><opponent>@GB</opponent><game-status>W 24-21</game-status><points>13</points></player><player id="plyr4482"><player-name>Dallas Clark, Ind&#xA0;TE</player-name><link>&lt;a href content="ajax#/ffl/format/pvopop/summary?leagueId=35734&amp;positionId=4&amp;playerId=70404&amp;seasonId=2008" class="flexpop" instance="_ppc"&gt;Cin&lt;/a&gt;</link><opponent>Cin</opponent><game-status>W 35-3</game-status><points>6</points></player><player id="plyr10452"><player-name>Adrian Peterson, Min&#xA0;RB</player-name><link>&lt;a href content="ajax#/ffl/format/pvopop/summary?leagueId=35734&amp;positionId=2&amp;playerId=70208&amp;seasonId=2008" class="flexpop" instance="_ppc"&gt;@Det&lt;/a&gt;</link><opponent>@Det</opponent><game-status>W 20-16</game-status><points>13</points></player><player id="plyr11688"><player-name>Dan Carpenter, Mia&#xA0;K</player-name><link>&lt;a href content="ajax#/ffl/format/pvopop/summary?leagueId=35734&amp;positionId=5&amp;playerId=70502&amp;seasonId=2008" class="flexpop" instance="_ppc"&gt;@Buf&lt;/a&gt;</link><opponent>@Buf</opponent><game-status>W 16-3</game-status><points>11</points></player><player id="plyr5633"><player-name>Jerricho Cotchery, NYJ&#xA0;WR</player-name><link>&lt;a href content="ajax#/ffl/format/pvopop/summary?leagueId=35734&amp;positionId=3&amp;playerId=70325&amp;seasonId=2008" class="flexpop" instance="_ppc"&gt;@SF&lt;/a&gt;</link><opponent>@SF</opponent><game-status>L 14-24</game-status><points>1</points></player></players></team></game>
