<?xml version="1.0"?>
<game file="/Users/richsanda/life/python/crawlers/espn/games/2012.9.3.xml"><team><header>Fly with Balloons Box Score</header><players><player id="plyr8444"><player-name>Heath Miller, Pit&#xA0;TE</player-name><link>&lt;a href content="ajax#/ffl/format/pvopop/summary?leagueId=35734&amp;positionId=4&amp;playerId=70419&amp;seasonId=2012" class="flexpop" instance="_ppc"&gt;@NYG&lt;/a&gt;</link><opponent>@NYG</opponent><game-status>W 24-20</game-status><points>4</points></player><player id="plyr14884"><player-name>Trent Richardson, Cle&#xA0;RB</player-name><link>&lt;a href content="ajax#/ffl/format/pvopop/summary?leagueId=35734&amp;positionId=2&amp;playerId=70233&amp;seasonId=2012" class="flexpop" instance="_ppc"&gt;Bal&lt;/a&gt;</link><opponent>Bal</opponent><game-status>L 15-25</game-status><points>15</points></player><player id="plyr60015"><player-name>Dolphins D/ST, Mia&#xA0;D/ST</player-name><link>&lt;a href content="ajax#/ffl/format/pvopop/summary?leagueId=35734&amp;positionId=16&amp;playerId=71611&amp;seasonId=2012" class="flexpop" instance="_ppc"&gt;@Ind&lt;/a&gt;</link><opponent>@Ind</opponent><game-status>L 20-23</game-status><points>2</points></player><player id="plyr1428"><player-name>Peyton Manning, Den&#xA0;QB</player-name><link>&lt;a href content="ajax#/ffl/format/pvopop/summary?leagueId=35734&amp;positionId=1&amp;playerId=70104&amp;seasonId=2012" class="flexpop" instance="_ppc"&gt;@Cin&lt;/a&gt;</link><opponent>@Cin</opponent><game-status>W 31-23</game-status><points>19</points></player><player id="plyr9354"><player-name>Robbie Gould, Chi&#xA0;K</player-name><link>&lt;a href content="ajax#/ffl/format/pvopop/summary?leagueId=35734&amp;positionId=5&amp;playerId=70510&amp;seasonId=2012" class="flexpop" instance="_ppc"&gt;@Ten&lt;/a&gt;</link><opponent>@Ten</opponent><game-status>W 51-20</game-status><points>16</points></player><player id="plyr12586"><player-name>Hakeem Nicks, NYG&#xA0;WR</player-name><link>&lt;a href content="ajax#/ffl/format/pvopop/summary?leagueId=35734&amp;positionId=3&amp;playerId=70323&amp;seasonId=2012" class="flexpop" instance="_ppc"&gt;Pit&lt;/a&gt;</link><opponent>Pit</opponent><game-status>L 20-24</game-status><points>1</points></player><player id="plyr13216"><player-name>Demaryius Thomas, Den&#xA0;WR</player-name><link>&lt;a href content="ajax#/ffl/format/pvopop/summary?leagueId=35734&amp;positionId=3&amp;playerId=70304&amp;seasonId=2012" class="flexpop" instance="_ppc"&gt;@Cin&lt;/a&gt;</link><opponent>@Cin</opponent><game-status>W 31-23</game-status><points>7</points></player><player id="plyr10467"><player-name>Dwayne Bowe, KC&#xA0;WR</player-name><link>&lt;a href content="ajax#/ffl/format/pvopop/summary?leagueId=35734&amp;positionId=3&amp;playerId=70324&amp;seasonId=2012" class="flexpop" instance="_ppc"&gt;@SD&lt;/a&gt;</link><opponent>@SD</opponent><game-status>L 13-31</game-status><points>5</points></player></players></team><team><header>Magoun Square Ruffians Box Score</header><players><player id="plyr11307"><player-name>Jamaal Charles, KC&#xA0;RB</player-name><link>&lt;a href content="ajax#/ffl/format/pvopop/summary?leagueId=35734&amp;positionId=2&amp;playerId=70224&amp;seasonId=2012" class="flexpop" instance="_ppc"&gt;@SD&lt;/a&gt;</link><opponent>@SD</opponent><game-status>L 13-31</game-status><points>5</points></player><player id="plyr60008"><player-name>Lions D/ST, Det&#xA0;D/ST</player-name><link>&lt;a href content="ajax#/ffl/format/pvopop/summary?leagueId=35734&amp;positionId=16&amp;playerId=71630&amp;seasonId=2012" class="flexpop" instance="_ppc"&gt;@Jac&lt;/a&gt;</link><opponent>@Jac</opponent><game-status>W 31-14</game-status><points>6</points></player><player id="plyr13553"><player-name>Victor Cruz, NYG&#xA0;WR</player-name><link>&lt;a href content="ajax#/ffl/format/pvopop/summary?leagueId=35734&amp;positionId=3&amp;playerId=70323&amp;seasonId=2012" class="flexpop" instance="_ppc"&gt;Pit&lt;/a&gt;</link><opponent>Pit</opponent><game-status>L 20-24</game-status><points>6</points></player><player id="plyr14054"><player-name>Kyle Rudolph, Min&#xA0;TE</player-name><link>&lt;a href content="ajax#/ffl/format/pvopop/summary?leagueId=35734&amp;positionId=4&amp;playerId=70426&amp;seasonId=2012" class="flexpop" instance="_ppc"&gt;@Sea&lt;/a&gt;</link><opponent>@Sea</opponent><game-status>L 20-30</game-status><points>0</points></player><player id="plyr13983"><player-name>A.J. Green, Cin&#xA0;WR</player-name><link>&lt;a href content="ajax#/ffl/format/pvopop/summary?leagueId=35734&amp;positionId=3&amp;playerId=70307&amp;seasonId=2012" class="flexpop" instance="_ppc"&gt;Den&lt;/a&gt;</link><opponent>Den</opponent><game-status>L 23-31</game-status><points>15</points></player><player id="plyr2549"><player-name>Michael Vick, Phi&#xA0;QB</player-name><link>&lt;a href content="ajax#/ffl/format/pvopop/summary?leagueId=35734&amp;positionId=1&amp;playerId=70118&amp;seasonId=2012" class="flexpop" instance="_ppc"&gt;@NO&lt;/a&gt;</link><opponent>@NO</opponent><game-status>L 13-28</game-status><points>19</points></player><player id="plyr4481"><player-name>Willis McGahee, Den&#xA0;RB</player-name><link>&lt;a href content="ajax#/ffl/format/pvopop/summary?leagueId=35734&amp;positionId=2&amp;playerId=70204&amp;seasonId=2012" class="flexpop" instance="_ppc"&gt;@Cin&lt;/a&gt;</link><opponent>@Cin</opponent><game-status>W 31-23</game-status><points>6</points></player><player id="plyr15683"><player-name>Justin Tucker, Bal&#xA0;K</player-name><link>&lt;a href content="ajax#/ffl/format/pvopop/summary?leagueId=35734&amp;positionId=5&amp;playerId=70505&amp;seasonId=2012" class="flexpop" instance="_ppc"&gt;@Cle&lt;/a&gt;</link><opponent>@Cle</opponent><game-status>W 25-15</game-status><points>6</points></player></players></team></game>
