<?xml version="1.0"?>
<game file="/Users/richsanda/life/python/crawlers/espn/games/2013.14.1.xml"><team><header>Jeff Knight All-Stars Box Score</header><players><player id="plyr11122"><player-name>Matt Prater, Den&#xA0;K</player-name><link>&lt;a href content="ajax#/ffl/format/pvopop/summary?leagueId=35734&amp;positionId=5&amp;playerId=70510&amp;seasonId=2013" class="flexpop" instance="_ppc"&gt;Ten&lt;/a&gt;</link><opponent>Ten</opponent><game-status>W 51-28</game-status><points>17</points></player><player id="plyr13215"><player-name>Dez Bryant, Dal&#xA0;WR</player-name><link>&lt;a href content="ajax#/ffl/format/pvopop/summary?leagueId=35734&amp;positionId=3&amp;playerId=70303&amp;seasonId=2013" class="flexpop" instance="_ppc"&gt;@Chi&lt;/a&gt;</link><opponent>@Chi</opponent><game-status>L 28-45</game-status><points>7</points></player><player id="plyr1428"><player-name>Peyton Manning, Den&#xA0;QB</player-name><link>&lt;a href content="ajax#/ffl/format/pvopop/summary?leagueId=35734&amp;positionId=1&amp;playerId=70110&amp;seasonId=2013" class="flexpop" instance="_ppc"&gt;Ten&lt;/a&gt;</link><opponent>Ten</opponent><game-status>W 51-28</game-status><points>33</points></player><player id="plyr10475"><player-name>Greg Olsen, Car&#xA0;TE</player-name><link>&lt;a href content="ajax#/ffl/format/pvopop/summary?leagueId=35734&amp;positionId=4&amp;playerId=70418&amp;seasonId=2013" class="flexpop" instance="_ppc"&gt;@NO&lt;/a&gt;</link><opponent>@NO</opponent><game-status>L 13-31</game-status><points>4</points></player><player id="plyr60026"><player-name>Seahawks D/ST, Sea&#xA0;D/ST</player-name><link>&lt;a href content="ajax#/ffl/format/pvopop/summary?leagueId=35734&amp;positionId=16&amp;playerId=71625&amp;seasonId=2013" class="flexpop" instance="_ppc"&gt;@SF&lt;/a&gt;</link><opponent>@SF</opponent><game-status>L 17-19</game-status><points>4</points></player><player id="plyr8475"><player-name>Vincent Jackson, TB&#xA0;WR</player-name><link>&lt;a href content="ajax#/ffl/format/pvopop/summary?leagueId=35734&amp;positionId=3&amp;playerId=70302&amp;seasonId=2013" class="flexpop" instance="_ppc"&gt;Buf&lt;/a&gt;</link><opponent>Buf</opponent><game-status>W 27-6</game-status><points>13</points></player><player id="plyr10452"><player-name>Adrian Peterson, Min&#xA0;RB</player-name><link>&lt;a href content="ajax#/ffl/format/pvopop/summary?leagueId=35734&amp;positionId=2&amp;playerId=70233&amp;seasonId=2013" class="flexpop" instance="_ppc"&gt;@Bal&lt;/a&gt;</link><opponent>@Bal</opponent><game-status>L 26-29</game-status><points>1</points></player><player id="plyr12514"><player-name>LeSean McCoy, Phi&#xA0;RB</player-name><link>&lt;a href content="ajax#/ffl/format/pvopop/summary?leagueId=35734&amp;positionId=2&amp;playerId=70208&amp;seasonId=2013" class="flexpop" instance="_ppc"&gt;Det&lt;/a&gt;</link><opponent>Det</opponent><game-status>W 34-20</game-status><points>41</points></player></players></team><team><header>Kidani Village Okapi Box Score</header><players><player id="plyr14005"><player-name>DeMarco Murray, Dal&#xA0;RB</player-name><link>&lt;a href content="ajax#/ffl/format/pvopop/summary?leagueId=35734&amp;positionId=2&amp;playerId=70203&amp;seasonId=2013" class="flexpop" instance="_ppc"&gt;@Chi&lt;/a&gt;</link><opponent>@Chi</opponent><game-status>L 28-45</game-status><points>16</points></player><player id="plyr60009"><player-name>Packers D/ST, GB&#xA0;D/ST</player-name><link>&lt;a href content="ajax#/ffl/format/pvopop/summary?leagueId=35734&amp;positionId=16&amp;playerId=71601&amp;seasonId=2013" class="flexpop" instance="_ppc"&gt;Atl&lt;/a&gt;</link><opponent>Atl</opponent><game-status>W 22-21</game-status><points>5</points></player><player id="plyr11923"><player-name>Steven Hauschka, Sea&#xA0;K</player-name><link>&lt;a href content="ajax#/ffl/format/pvopop/summary?leagueId=35734&amp;positionId=5&amp;playerId=70525&amp;seasonId=2013" class="flexpop" instance="_ppc"&gt;@SF&lt;/a&gt;</link><opponent>@SF</opponent><game-status>L 17-19</game-status><points>5</points></player><player id="plyr4461"><player-name>Andre Johnson, Hou&#xA0;WR</player-name><link>&lt;a href content="ajax#/ffl/format/pvopop/summary?leagueId=35734&amp;positionId=3&amp;playerId=70330&amp;seasonId=2013" class="flexpop" instance="_ppc"&gt;@Jac&lt;/a&gt;</link><opponent>@Jac</opponent><game-status>L 20-27</game-status><points>17</points></player><player id="plyr5941"><player-name>Wes Welker, Den&#xA0;WR</player-name><link>&lt;a href content="ajax#/ffl/format/pvopop/summary?leagueId=35734&amp;positionId=3&amp;playerId=70310&amp;seasonId=2013" class="flexpop" instance="_ppc"&gt;Ten&lt;/a&gt;</link><opponent>Ten</opponent><game-status>W 51-28</game-status><points>12</points></player><player id="plyr15009"><player-name>Alfred Morris, Wsh&#xA0;RB</player-name><link>&lt;a href content="ajax#/ffl/format/pvopop/summary?leagueId=35734&amp;positionId=2&amp;playerId=70212&amp;seasonId=2013" class="flexpop" instance="_ppc"&gt;KC&lt;/a&gt;</link><opponent>KC</opponent><game-status>L 10-45</game-status><points>3</points></player><player id="plyr13994"><player-name>Cam Newton, Car&#xA0;QB</player-name><link>&lt;a href content="ajax#/ffl/format/pvopop/summary?leagueId=35734&amp;positionId=1&amp;playerId=70118&amp;seasonId=2013" class="flexpop" instance="_ppc"&gt;@NO&lt;/a&gt;</link><opponent>@NO</opponent><game-status>L 13-31</game-status><points>14</points></player><player id="plyr13232"><player-name>Jimmy Graham, NO&#xA0;TE</player-name><link>&lt;a href content="ajax#/ffl/format/pvopop/summary?leagueId=35734&amp;positionId=4&amp;playerId=70429&amp;seasonId=2013" class="flexpop" instance="_ppc"&gt;Car&lt;/a&gt;</link><opponent>Car</opponent><game-status>W 31-13</game-status><points>17</points></player></players></team></game>
