<game season="2013" scoringPeriod="15" team="1">
   <team>
      <header>Jeff Knight All-Stars Box Score</header>
      <players>
         <player id="plyr11258">
            <player-slot/>
            <player-name>Chris Johnson, NYJ RB</player-name>
            <link/>
            <opponent>@Car</opponent>
            <game-status>L 20-30</game-status>
            <points>15</points>
         </player>
         <player id="plyr11122">
            <player-slot/>
            <player-name>Matt Prater, Den K</player-name>
            <link/>
            <opponent>SD</opponent>
            <game-status>L 20-27</game-status>
            <points>9</points>
         </player>
         <player id="plyr13215">
            <player-slot/>
            <player-name>Dez Bryant, Dal WR</player-name>
            <link/>
            <opponent>GB</opponent>
            <game-status>L 36-37</game-status>
            <points>23</points>
         </player>
         <player id="plyr1428">
            <player-slot/>
            <player-name>Peyton Manning, Den QB</player-name>
            <link/>
            <opponent>SD</opponent>
            <game-status>L 20-27</game-status>
            <points>17</points>
         </player>
         <player id="plyr10475">
            <player-slot/>
            <player-name>Greg Olsen, Car TE</player-name>
            <link/>
            <opponent>NYJ</opponent>
            <game-status>W 30-20</game-status>
            <points>8</points>
         </player>
         <player id="plyr60026">
            <player-slot/>
            <player-name>Seahawks D/ST, Sea D/ST</player-name>
            <link/>
            <opponent>@NYG</opponent>
            <game-status>W 23-0</game-status>
            <points>24</points>
         </player>
         <player id="plyr8475">
            <player-slot/>
            <player-name>Vincent Jackson, TB WR</player-name>
            <link/>
            <opponent>SF</opponent>
            <game-status>L 14-33</game-status>
            <points>11</points>
         </player>
         <player id="plyr12514">
            <player-slot/>
            <player-name>LeSean McCoy, Phi RB</player-name>
            <link/>
            <opponent>@Min</opponent>
            <game-status>L 30-48</game-status>
            <points>9</points>
         </player>
      </players>
   </team>
   <team>
      <header>Magoun Square Ruffians Box Score</header>
      <players>
         <player id="plyr11307">
            <player-slot/>
            <player-name>Jamaal Charles, KC RB</player-name>
            <link/>
            <opponent>@Oak</opponent>
            <game-status>W 56-31</game-status>
            <points>57</points>
         </player>
         <player id="plyr15705">
            <player-slot/>
            <player-name>Josh Gordon, Cle WR</player-name>
            <link/>
            <opponent>Chi</opponent>
            <game-status>L 31-38</game-status>
            <points>14</points>
         </player>
         <player id="plyr14204">
            <player-slot/>
            <player-name>Julius Thomas, Den TE</player-name>
            <link/>
            <opponent>SD</opponent>
            <game-status>L 20-27</game-status>
            <points>4</points>
         </player>
         <player id="plyr60004">
            <player-slot/>
            <player-name>Bengals D/ST, Cin D/ST</player-name>
            <link/>
            <opponent>@Pit</opponent>
            <game-status>L 20-30</game-status>
            <points>-1</points>
         </player>
         <player id="plyr12516">
            <player-slot/>
            <player-name>Knowshon Moreno, Mia RB</player-name>
            <link/>
            <opponent>NE</opponent>
            <game-status>W 24-20</game-status>
            <points>4</points>
         </player>
         <player id="plyr13983">
            <player-slot/>
            <player-name>A.J. Green, Cin WR</player-name>
            <link/>
            <opponent>@Pit</opponent>
            <game-status>L 20-30</game-status>
            <points>9</points>
         </player>
         <player id="plyr9329">
            <player-slot/>
            <player-name>Nick Novak, SD K</player-name>
            <link/>
            <opponent>@Den</opponent>
            <game-status>W 27-20</game-status>
            <points>9</points>
         </player>
         <player id="plyr14874">
            <player-slot/>
            <player-name>Andrew Luck, Ind QB</player-name>
            <link/>
            <opponent>Hou</opponent>
            <game-status>W 25-3</game-status>
            <points>15</points>
         </player>
      </players>
   </team>
</game>
