<game season="2017" scoringPeriod="15" team="11">
   <team>
      <header>Smooth Criminals Box Score</header>
      <players>
         <player id="plyr2330">
            <player-slot>QB</player-slot>
            <player-name>Tom Brady, NE QB</player-name>
            <link/>
            <opponent>@Pit</opponent>
            <game-status>W 27-24</game-status>
            <points>15</points>
         </player>
         <player id="plyr10456">
            <player-slot>RB</player-slot>
            <player-name>Marshawn Lynch, Oak RB</player-name>
            <link/>
            <opponent>Dal</opponent>
            <game-status>L 17-20</game-status>
            <points>8</points>
         </player>
         <player id="plyr15971">
            <player-slot>RB/WR</player-slot>
            <player-name>Rex Burkhead, NE RB   D</player-name>
            <link/>
            <opponent>@Pit</opponent>
            <game-status>W 27-24</game-status>
            <points>7</points>
         </player>
         <player id="plyr16781">
            <player-slot>WR</player-slot>
            <player-name>Paul Richardson, Sea WR</player-name>
            <link/>
            <opponent>LAR</opponent>
            <game-status>L 7-42</game-status>
            <points>1</points>
         </player>
         <player id="plyr16787">
            <player-slot>WR/TE</player-slot>
            <player-name>Marqise Lee, Jax WR   Q</player-name>
            <link/>
            <opponent>Hou</opponent>
            <game-status>W 45-7</game-status>
            <points>0</points>
         </player>
         <player id="plyr17822">
            <player-slot>TE</player-slot>
            <player-name>Hunter Henry*, LAC TE   IR</player-name>
            <link/>
            <opponent>@KC</opponent>
            <game-status>L 13-30</game-status>
            <points>2</points>
         </player>
         <player id="plyr60018">
            <player-slot>D/ST</player-slot>
            <player-name>Saints D/ST D/ST</player-name>
            <link/>
            <opponent>NYJ</opponent>
            <game-status>W 31-19</game-status>
            <points>5</points>
         </player>
         <player id="plyr10636">
            <player-slot>K</player-slot>
            <player-name>Mason Crosby, GB K</player-name>
            <link/>
            <opponent>@Car</opponent>
            <game-status>L 24-31</game-status>
            <points>6</points>
         </player>
      </players>
   </team>
   <team>
      <header>Westerly Donnabairds Box Score</header>
      <players>
         <player id="plyr16724">
            <player-slot>QB</player-slot>
            <player-name>Blake Bortles, Jax QB</player-name>
            <link/>
            <opponent>Hou</opponent>
            <game-status>W 45-7</game-status>
            <points>27</points>
         </player>
         <player id="plyr17586">
            <player-slot>RB</player-slot>
            <player-name>Melvin Gordon, LAC RB</player-name>
            <link/>
            <opponent>@KC</opponent>
            <game-status>L 13-30</game-status>
            <points>22</points>
         </player>
         <player id="plyr11247">
            <player-slot>RB/WR</player-slot>
            <player-name>Jonathan Stewart, Car RB</player-name>
            <link/>
            <opponent>GB</opponent>
            <game-status>W 31-24</game-status>
            <points>2</points>
         </player>
         <player id="plyr5528">
            <player-slot>WR</player-slot>
            <player-name>Larry Fitzgerald, Ari WR</player-name>
            <link/>
            <opponent>@Wsh</opponent>
            <game-status>L 15-20</game-status>
            <points>6</points>
         </player>
         <player id="plyr14922">
            <player-slot>WR/TE</player-slot>
            <player-name>Mohamed Sanu, Atl WR   Q</player-name>
            <link/>
            <opponent>@TB</opponent>
            <game-status>W 24-21</game-status>
            <points>2</points>
         </player>
         <player id="plyr15847">
            <player-slot>TE</player-slot>
            <player-name>Travis Kelce, KC TE   Q</player-name>
            <link/>
            <opponent>LAC</opponent>
            <game-status>W 30-13</game-status>
            <points>4</points>
         </player>
         <player id="plyr60022">
            <player-slot>D/ST</player-slot>
            <player-name>Cardinals D/ST D/ST</player-name>
            <link/>
            <opponent>@Wsh</opponent>
            <game-status>L 15-20</game-status>
            <points>3</points>
         </player>
         <player id="plyr14322">
            <player-slot>K</player-slot>
            <player-name>Dan Bailey, Dal K</player-name>
            <link/>
            <opponent>@Oak</opponent>
            <game-status>W 20-17</game-status>
            <points>9</points>
         </player>
      </players>
   </team>
</game>
