<game season="2017" scoringPeriod="9" team="7">
   <team>
      <header>Apponequet Justins Box Score</header>
      <players>
         <player id="plyr11237">
            <player-slot>QB</player-slot>
            <player-name>Matt Ryan, Atl QB</player-name>
            <link/>
            <opponent>@Car</opponent>
            <game-status>L 17-20</game-status>
            <points>20</points>
         </player>
         <player id="plyr10452">
            <player-slot>RB</player-slot>
            <player-name>Adrian Peterson, Ari RB</player-name>
            <link/>
            <opponent>@SF</opponent>
            <game-status>W 20-10</game-status>
            <points>15</points>
         </player>
         <player id="plyr14129">
            <player-slot>RB/WR</player-slot>
            <player-name>Bilal Powell, NYJ RB</player-name>
            <link/>
            <opponent>Buf</opponent>
            <game-status>W 34-21</game-status>
            <points>7</points>
         </player>
         <player id="plyr17810">
            <player-slot>WR</player-slot>
            <player-name>Josh Doctson, Wsh WR</player-name>
            <link/>
            <opponent>@Sea</opponent>
            <game-status>W 17-14</game-status>
            <points>5</points>
         </player>
         <player id="plyr14221">
            <player-slot>WR/TE</player-slot>
            <player-name>Doug Baldwin, Sea WR</player-name>
            <link/>
            <opponent>Wsh</opponent>
            <game-status>L 14-17</game-status>
            <points>18</points>
         </player>
         <player id="plyr9592">
            <player-slot>TE</player-slot>
            <player-name>Vernon Davis, Wsh TE</player-name>
            <link/>
            <opponent>@Sea</opponent>
            <game-status>W 17-14</game-status>
            <points>7</points>
         </player>
         <player id="plyr60007">
            <player-slot>D/ST</player-slot>
            <player-name>Broncos D/ST D/ST</player-name>
            <link/>
            <opponent>@Phi</opponent>
            <game-status>L 23-51</game-status>
            <points>0</points>
         </player>
         <player id="plyr9354">
            <player-slot>K</player-slot>
            <player-name>Robbie Gould, SF K</player-name>
            <link/>
            <opponent>Ari</opponent>
            <game-status>L 10-20</game-status>
            <points>5</points>
         </player>
      </players>
   </team>
   <team>
      <header>Point Place Vikings Box Score</header>
      <players>
         <player id="plyr17907">
            <player-slot>QB</player-slot>
            <player-name>Dak Prescott, Dal QB</player-name>
            <link/>
            <opponent>KC</opponent>
            <game-status>W 28-17</game-status>
            <points>25</points>
         </player>
         <player id="plyr14005">
            <player-slot>RB</player-slot>
            <player-name>DeMarco Murray, Ten RB</player-name>
            <link/>
            <opponent>Bal</opponent>
            <game-status>W 23-20</game-status>
            <points>3</points>
         </player>
         <player id="plyr13213">
            <player-slot>RB/WR</player-slot>
            <player-name>LeGarrette Blount, Phi RB</player-name>
            <link/>
            <opponent>Den</opponent>
            <game-status>W 51-23</game-status>
            <points>3</points>
         </player>
         <player id="plyr13983">
            <player-slot>WR</player-slot>
            <player-name>A.J. Green, Cin WR</player-name>
            <link/>
            <opponent>@Jax</opponent>
            <game-status>L 7-23</game-status>
            <points>0</points>
         </player>
         <player id="plyr12579">
            <player-slot>WR/TE</player-slot>
            <player-name>Jeremy Maclin, Bal WR</player-name>
            <link/>
            <opponent>@Ten</opponent>
            <game-status>L 20-23</game-status>
            <points>9</points>
         </player>
         <player id="plyr12537">
            <player-slot>TE</player-slot>
            <player-name>Jared Cook, Oak TE</player-name>
            <link/>
            <opponent>@Mia</opponent>
            <game-status>W 27-24</game-status>
            <points>14</points>
         </player>
         <player id="plyr60015">
            <player-slot>D/ST</player-slot>
            <player-name>Dolphins D/ST D/ST</player-name>
            <link/>
            <opponent>Oak</opponent>
            <game-status>L 24-27</game-status>
            <points>4</points>
         </player>
         <player id="plyr15683">
            <player-slot>K</player-slot>
            <player-name>Justin Tucker, Bal K</player-name>
            <link/>
            <opponent>@Ten</opponent>
            <game-status>L 20-23</game-status>
            <points>9</points>
         </player>
      </players>
   </team>
</game>
